schemaworks/__init__.py
schemaworks/converter.py
schemaworks/utils.py
schemaworks/validators.py
schemaworks-1.2.2.dist-info/LICENSE
schemaworks-1.2.2.dist-info/METADATA
schemaworks-1.2.2.dist-info/WHEEL
schemaworks-1.2.2.dist-info/RECORD
