Metadata-Version: 2.3
Name: schemaworks
Version: 1.2.2
Summary: A schema conversion toolkit for JSON, Spark, PyIceberg and SQL formats.
License: GNU GPLv3
Keywords: schema,conversion,spark,json,sql,data-engineering
Author: Anatol Jurenkow
Author-email: azurius@t-online.de
Requires-Python: >=3.10
Classifier: License :: OSI Approved :: MIT License
Classifier: Programming Language :: Python :: 3.10
Classifier: Programming Language :: Python :: 3.11
Classifier: Programming Language :: Python :: 3.12
Classifier: Intended Audience :: Developers
Classifier: Topic :: Software Development :: Libraries :: Python Modules
Provides-Extra: dev
Requires-Dist: boto3 (>=1.34.0,<2.0.0)
Requires-Dist: jsonschema
Requires-Dist: moto (>=5.1.1,<6.0.0) ; extra == "dev"
Requires-Dist: numpy
Requires-Dist: pyiceberg (>=0.9.1,<0.10.0)
Requires-Dist: pyspark
Requires-Dist: pytest (>=8.3.5,<9.0.0) ; extra == "dev"
Requires-Dist: pytest-cov (>=6.0.0,<7.0.0) ; extra == "dev"
Requires-Dist: pytest-mock (>=3.14.0,<4.0.0) ; extra == "dev"
Requires-Dist: ruff (>=0.9.9,<1.0.0) ; extra == "dev"
Project-URL: Homepage, https://github.com/anatol-ju/schemaworks
Project-URL: Repository, https://github.com/anatol-ju/schemaworks
